znn/__init__.py
znn/constants.py
znn/abi/__init__.py
znn/abi/abi.py
znn/abi/registry.py
znn/abi/utils.py
znn/api/__init__.py
znn/api/ledger.py
znn/api/stats.py
znn/api/subscribe.py
znn/api/embedded/__init__.py
znn/api/embedded/accelerator.py
znn/api/embedded/pillar.py
znn/api/embedded/plasma.py
znn/api/embedded/sentinel.py
znn/api/embedded/stake.py
znn/api/embedded/swap.py
znn/api/embedded/token.py
znn/client/__init__.py
znn/client/websocket.py
znn/embedded/__init__.py
znn/embedded/constants.py
znn/embedded/definitions.py
znn/model/__init__.py
znn/model/nom/__init__.py
znn/model/nom/account_block.py
znn/model/primitives/__init__.py
znn/model/primitives/address.py
znn/model/primitives/hash.py
znn/model/primitives/hash_height.py
znn/model/primitives/token_standard.py
znn/wallet/__init__.py
znn/wallet/keypair.py
znn/wallet/keystore.py
znn/wallet/transact.py
pyznn-0.0.1.dist-info/LICENSE
pyznn-0.0.1.dist-info/METADATA
pyznn-0.0.1.dist-info/WHEEL
pyznn-0.0.1.dist-info/top_level.txt
pyznn-0.0.1.dist-info/RECORD
